#######################################################################################################################################
<poster>BigBallzBaby</poster>
<fanart>http://thetvdb.com/banners/fanart/original/73314-6.jpg</fanart>
#######################################################################################################################################
<info>
<message>[COLOR red]REPORT dead links to (Twitter) @BigBallzBaby ... ENJOY!![/COLOR]</message>
<thumbnail>http://s20.postimg.org/jvq2l8xel/TNPB.png</thumbnail>
</info>
#######################################################################################################################################

<item>
<title>5x1 Cleanin'</title>
<link>http://www.putlocker.com/file/A91EC727341BB7CC</link>
<thumbnail>http://thetvdb.com/banners/_cache/episodes/73314/112019.jpg</thumbnail>
</item>

<item>
<title>5x2 Book Clubbin'</title>
<link>http://www.putlocker.com/file/41576E2E5FA6D98D</link>
<thumbnail>http://thetvdb.com/banners/_cache/episodes/73314/112020.jpg</thumbnail>
</item>

<item>
<title>5x3 Panickin'</title>
<link>http://www.putlocker.com/file/2D3A26FA83D885EE</link>
<thumbnail>http://thetvdb.com/banners/_cache/episodes/73314/112021.jpg</thumbnail>
</item>

<item>
<title>5x4 Huntin' Shootin' & Fishin'</title>
<link>http://www.putlocker.com/file/A5B7F92701B23707</link>
<thumbnail>http://thetvdb.com/banners/_cache/episodes/73314/112022.jpg</thumbnail>
</item>

<item>
<title>5x5 Birthin'</title>
<link>http://www.putlocker.com/file/5EBF1D72675F4264</link>
<thumbnail>http://thetvdb.com/banners/_cache/episodes/73314/112023.jpg</thumbnail>
</item>

<item>
<title>5x6 Schmoozin'</title>
<link>http://www.putlocker.com/file/A35F525AB9B0AFF4</link>
<thumbnail>http://thetvdb.com/banners/_cache/episodes/73314/112024.jpg</thumbnail>
</item>

<item>
<title>5x7 Exploitin'</title>
<link>http://www.putlocker.com/file/7956C20221DDCD01</link>
<thumbnail>http://thetvdb.com/banners/_cache/episodes/73314/112025.jpg</thumbnail>
</item>

