#######################################################################################################################################
<poster>TNPB!</poster>
<fanart>http://s20.postimg.org/f1ov06599/fanart2.png</fanart>
#######################################################################################################################################
<info>
<message>[COLOR red]Welcome to  kIdZoNe! [/COLOR]</message>
<thumbnail>http://s20.postimg.org/jvq2l8xel/TNPB.png</thumbnail>
</info>
##############################################################################################################################

<item>
<title>Cool Runnings (1993)</title>
</link>http://85.12.8.91/index.php?file=2144&start=0&hd=0&auth=0&type=flv&tv=0</link>
<thumbnail>http://ia.media-imdb.com/images/M/MV5BMTQ5MjQ1MTEzOF5BMl5BanBnXkFtZTcwMjIyNjgxMQ@@._V1_SY317_CR2,0,214,317_.jpg</thumbnail>
</item>

<item>
<title>Speed Racer (2008)</title>
</link>http://85.12.8.91/index.php?file=2129&start=0&hd=0&auth=0&type=flv&tv=0</link>
<thumbnail>http://ia.media-imdb.com/images/M/MV5BMTA5MjgxMDE4OTVeQTJeQWpwZ15BbWU3MDgyNjc4NjE@._V1_SY317_CR0,0,214,317_.jpg</thumbnail>
</item>

<item>
<title>The NeverEnding Story (1984)</title>
</link>http://85.12.8.91/index.php?file=1981&start=0&hd=0&auth=0&type=flv&tv=0</link>
<thumbnail>http://ia.media-imdb.com/images/M/MV5BMTI3MDA3NTQ0MF5BMl5BanBnXkFtZTcwNDEwMDMyMQ@@._V1_SY317_CR3,0,214,317_.jpg</thumbnail>
</item>

<item>
<title>Hugo (2011)</title>
</link>http://85.12.8.91/index.php?file=1979&start=0&hd=0&auth=0&type=flv&tv=0</link>
<thumbnail>http://ia.media-imdb.com/images/M/MV5BMjAzNzk5MzgyNF5BMl5BanBnXkFtZTcwOTE4NDU5Ng@@._V1_SX214_.jpg</thumbnail>
</item>

<item>
<title>We Bought a Zoo (2011)</title>
</link>http://85.12.8.91/index.php?file=1977&start=0&hd=0&auth=0&type=flv&tv=0</link>
<thumbnail>http://ia.media-imdb.com/images/M/MV5BMTQ0MTE3OTUwMl5BMl5BanBnXkFtZTcwODg5NjgwNw@@._V1_SX214_.jpg</thumbnail>
</item>

<item>
<title>Planet 51 (2009)</title>
</link>http://85.12.8.91/index.php?file=1973&start=0&hd=0&auth=0&type=flv&tv=0</link>
<thumbnail>http://ia.media-imdb.com/images/M/MV5BMTUyOTAyNTA5Ml5BMl5BanBnXkFtZTcwODU2OTM0Mg@@._V1_SX214_.jpg</thumbnail>
</item>

<item>
<title>Evan Almighty (2007)</title>
</link>http://85.12.8.91/index.php?file=1887&start=0&hd=0&auth=0&type=flv&tv=0</link>
<thumbnail>http://ia.media-imdb.com/images/M/MV5BMTUxMTEzODYxMV5BMl5BanBnXkFtZTcwNzQ4ODU0MQ@@._V1_SY317_CR0,0,214,317_.jpg</thumbnail>
</item>

<item>
<title>Around the World in 80 Days (2004)</title>
</link>http://85.12.8.91/index.php?file=1941&start=0&hd=0&auth=0&type=flv&tv=0</link>
<thumbnail>http://ia.media-imdb.com/images/M/MV5BMTc4MTkxMjQ2NF5BMl5BanBnXkFtZTcwNzE0NzUyMQ@@._V1_SX214_.jpg</thumbnail>
</item>

<item>
<title>The Muppet Movie (1979)</title>
</link>http://85.12.8.91/index.php?file=1913&start=0&hd=0&auth=0&type=flv&tv=0</link>
<thumbnail>http://ia.media-imdb.com/images/M/MV5BMTgzOTg2MTM3M15BMl5BanBnXkFtZTcwMzgxMzEzMQ@@._V1_SY317_CR5,0,214,317_.jpg</thumbnail>
</item>

<item>
<title>The Pagemaster (1994)</title>
</link>http://85.12.8.91/index.php?file=1911&start=0&hd=0&auth=0&type=flv&tv=0</link>
<thumbnail>http://ia.media-imdb.com/images/M/MV5BMTc2MjY4MjYwN15BMl5BanBnXkFtZTcwNDI3MjAyMQ@@._V1_SY317_CR4,0,214,317_.jpg</thumbnail>
</item>

<item>
<title>Lemony Snicket's A Series of Unfortunate Events (2004)</title>
</link>http://85.12.8.91/index.php?file=1899&start=0&hd=0&auth=0&type=flv&tv=0</link>
<thumbnail>http://d3gtl9l2a4fn1j.cloudfront.net/t/p/w500/dHQMAj9E2G2ewjN1aCOPubsZaj1.jpg</thumbnail>
</item>

<item>
<title>The Croods (2013)</title>
</link>http://85.12.8.91/index.php?file=2140&start=0&hd=0&auth=0&type=flv&tv=0</link>
<thumbnail>http://ia.media-imdb.com/images/M/MV5BMTcyOTc2OTA1Ml5BMl5BanBnXkFtZTcwOTI1MjkzOQ@@._V1_SY317_CR0,0,214,317_.jpg</thumbnail>
</item>

<item>
<title>Hotel for Dogs (2009)</title>
</link>http://85.12.8.91/index.php?file=1828&start=0&hd=0&auth=0&type=flv&tv=0</link>
<thumbnail>http://ia.media-imdb.com/images/M/MV5BMTI5NjkxOTE5MF5BMl5BanBnXkFtZTcwMTcxNTAwMg@@._V1_SY317_CR0,0,214,317_.jpg</thumbnail>
</item>

<item>
<title>Night at the Museum (2006)</title>
</link>http://85.12.8.91/index.php?file=1857&start=0&hd=0&auth=0&type=flv&tv=0</link>
<thumbnail>http://ia.media-imdb.com/images/M/MV5BMTQyOTM4MDMxN15BMl5BanBnXkFtZTcwODg5NTQzMw@@._V1_SY317_CR1,0,214,317_.jpg</thumbnail>
</item>

<item>
<title>Night at the Museum: Battle of the Smithsonian (2009)</title>
</link>http://85.12.8.91/index.php?file=1858&start=0&hd=0&auth=0&type=flv&tv=0</link>
<thumbnail>http://ia.media-imdb.com/images/M/MV5BMjAzMzc0MzM3MF5BMl5BanBnXkFtZTcwNjUzODkyMg@@._V1_SX214_.jpg</thumbnail>
</item>

<item>
<title>Epic (2013)</title>
</link>http://85.12.8.91/index.php?file=1919&start=0&hd=0&auth=0&type=flv&tv=0</link>
<thumbnail>http://ia.media-imdb.com/images/M/MV5BMTgyNDYwNzE5NV5BMl5BanBnXkFtZTcwMzUyODM5OA@@._V1_SY317_CR0,0,214,317_.jpg</thumbnail>
</item>

<item>
<title>Despicable Me (2010)</title>
</link>http://85.12.8.91/index.php?file=1653&start=0&hd=0&auth=0&type=flv&tv=0</link>
<thumbnail>http://ia.media-imdb.com/images/M/MV5BMTY3NjY0MTQ0Nl5BMl5BanBnXkFtZTcwMzQ2MTc0Mw@@._V1_SY317_CR0,0,214,317_.jpg</thumbnail>
</item>

<item>
<title>Dino Time (2012)</title>
</link>http://85.12.8.91/index.php?file=1642&start=0&hd=0&auth=0&type=flv&tv=0</link>
<thumbnail>http://ia.media-imdb.com/images/M/MV5BMTYzOTM3NjY4MF5BMl5BanBnXkFtZTcwMzMzMDY2OA@@._V1_SY317_CR0,0,214,317_.jpg</thumbnail>
</item>

<item>
<title>The Emperor's New Groove (2000)</title>
</link>http://85.12.8.91/index.php?file=1611&start=0&hd=0&auth=0&type=flv&tv=0</link>
<thumbnail>http://ia.media-imdb.com/images/M/MV5BMTMxNTY0MzU1MV5BMl5BanBnXkFtZTYwODgwNjQ3._V1_SY317_CR7,0,214,317_.jpg</thumbnail>
</item>

<item>
<title>The Emperor's New Groove 2: Kronk's New Groove (2005)</title>
</link>http://85.12.8.91/index.php?file=1612&start=0&hd=0&auth=0&type=flv&tv=0</link>
<thumbnail>http://ia.media-imdb.com/images/M/MV5BMTQ5NjQyOTU2MF5BMl5BanBnXkFtZTcwOTU0NjMzMQ@@._V1_SY317_CR8,0,214,317_.jpg</thumbnail>
</item>

<item>
<title>Oz the Great and Powerful (2013)</title>
</link>http://85.12.8.91/index.php?file=1561&start=0&hd=0&auth=0&type=flv&tv=0</link>
<thumbnail>http://ia.media-imdb.com/images/M/MV5BMjMyMzQ1ODM1MF5BMl5BanBnXkFtZTcwMjE2MTQxOQ@@._V1_SY317_CR0,0,214,317_.jpg</thumbnail>
</item>

<item>
<title>Escape from Planet Earth (2013)</title>
</link>http://85.12.8.91/index.php?file=1549&start=0&hd=0&auth=0&type=flv&tv=0</link>
<thumbnail>http://ia.media-imdb.com/images/M/MV5BMTQyMTk4NjkyMl5BMl5BanBnXkFtZTcwMzA2OTY4OA@@._V1_SX214_.jpg</thumbnail>
</item>

<item>
<title>Red Dog (2011)</title>
</link>http://85.12.8.91/index.php?file=1536&start=0&hd=0&auth=0&type=flv&tv=0</link>
<thumbnail>http://ia.media-imdb.com/images/M/MV5BMjAwNjMwNDQ0NF5BMl5BanBnXkFtZTcwMzE2NTExOA@@._V1_SY317_CR6,0,214,317_.jpg</thumbnail>
</item>

<item>
<title>The Smurfs (2011)</title>
</link>http://85.12.8.91/index.php?file=1514&start=0&hd=0&auth=0&type=flv&tv=0</link>
<thumbnail>http://ia.media-imdb.com/images/M/MV5BMTY4MDc2NzQ4MF5BMl5BanBnXkFtZTcwNDc5OTU2NA@@._V1_SY317_CR0,0,214,317_.jpg</thumbnail>
</item>

<item>
<title>Beauty and the Beast (1991)</title>
</link>http://85.12.8.91/index.php?file=1507&start=0&hd=0&auth=0&type=flv&tv=0</link>
<thumbnail>http://ia.media-imdb.com/images/M/MV5BMTc0MzM1Njk1OV5BMl5BanBnXkFtZTcwNjQxMTkwNw@@._V1_SX214_.jpg</thumbnail>
</item>

<item>
<title>Gulliver's Travels (2011)</title>
</link>http://85.12.8.91/index.php?file=1497&start=0&hd=0&auth=0&type=flv&tv=0</link>
<thumbnail>http://ia.media-imdb.com/images/M/MV5BMTU0NTUwOTM3Nl5BMl5BanBnXkFtZTcwMDA3NjIwNA@@._V1_SX214_.jpg</thumbnail>
</item>

<item>
<title>Mirror Mirror (2012)</title>
</link>http://85.12.8.91/index.php?file=1495&start=0&hd=0&auth=0&type=flv&tv=0</link>
<thumbnail>http://ia.media-imdb.com/images/M/MV5BMTExMjU4MTUwNTVeQTJeQWpwZ15BbWU3MDk2MzkwMjc@._V1_SX214_.jpg</thumbnail>
</item>

<item>
<title>Barbie in the Pink Shoes (2013)</title>
</link>http://85.12.8.91/index.php?file=1455&start=0&hd=0&auth=0&type=flv&tv=0</link>
<thumbnail>http://ia.media-imdb.com/images/M/MV5BMjQyMzYxNTQxNl5BMl5BanBnXkFtZTcwMjI1NDExOQ@@._V1_SY317_CR9,0,214,317_.jpg</thumbnail>
</item>

<item>
<title>Aloha, Scooby-Doo! (2005)</title>
</link>http://85.12.8.91/index.php?file=1419&start=0&hd=0&auth=0&type=flv&tv=0</link>
<thumbnail>http://upload.wikimedia.org/wikipedia/en/thumb/3/3f/Aloha,_Scooby-Doo!.jpg/220px-Aloha,_Scooby-Doo!.jpg</thumbnail>
</item>

<item>
<title>Tom and Jerry in Shiver Me Whiskers (2006)</title>
</link>http://85.12.8.91/index.php?file=1460&start=0&hd=0&auth=0&type=flv&tv=0</link>
<thumbnail>http://images1.wikia.nocookie.net/__cb20110403133421/tomandjerry/images/6/6c/Tom-and-Jerry-Shiver-Me-Whiskers-1-.jpg</thumbnail>
</item>

<item>
<title>The Pink Panther (2006)</title>
</link>http://85.12.8.91/index.php?file=1481&start=0&hd=0&auth=0&type=flv&tv=0</link>
<thumbnail>http://ia.media-imdb.com/images/M/MV5BMTkyMTAwNzg2NV5BMl5BanBnXkFtZTcwNTE0MTgyMQ@@._V1_SX214_.jpg</thumbnail>
</item>

<item>
<title>The Pink Panther 2 (2009)</title>
</link>http://85.12.8.91/index.php?file=1482&start=0&hd=0&auth=0&type=flv&tv=0</link>
<thumbnail>http://ia.media-imdb.com/images/M/MV5BMTIyOTI2ODY2MF5BMl5BanBnXkFtZTcwMzU2MTYxMg@@._V1_SX214_.jpg</thumbnail>
</item>

<item>
<title>The Sandlot (1993)</title>
</link>http://85.12.8.91/index.php?file=1281&start=0&hd=0&auth=0&type=flv&tv=0</link>
<thumbnail>http://ia.media-imdb.com/images/M/MV5BMTkwMjkyNzQ0MV5BMl5BanBnXkFtZTYwMzMzMjE5._V1_SX214_.jpg</thumbnail>
</item>

<item>
<title>Nim's Island (2008)</title>
</link>http://85.12.8.91/index.php?file=1326&start=0&hd=0&auth=0&type=flv&tv=0</link>
<thumbnail>http://ia.media-imdb.com/images/M/MV5BMTA0OTk0NjIwMDleQTJeQWpwZ15BbWU3MDg3NjM0NTE@._V1_SY317_CR0,0,214,317_.jpg</thumbnail>
</item>

<item>
<title>Eragon (2006)</title>
</link>http://85.12.8.91/index.php?file=1361&start=0&hd=0&auth=0&type=flv&tv=0</link>
<thumbnail>http://ia.media-imdb.com/images/M/MV5BMTg2ODkzMjgxNV5BMl5BanBnXkFtZTYwOTYzNDA3._V1_SY317_CR0,0,214,317_.jpg</thumbnail>
</item>

<item>
<title>Tooth Fairy (2010)</title>
</link>http://85.12.8.91/index.php?file=1366&start=0&hd=0&auth=0&type=flv&tv=0</link>
<thumbnail>http://ia.media-imdb.com/images/M/MV5BMTQ4NjQzMjQxNF5BMl5BanBnXkFtZTcwNTEzMDY4Mg@@._V1_SX214_.jpg</thumbnail>
</item>

<item>
<title>Rio (2011)</title>
</link>http://85.12.8.91/index.php?file=1376&start=0&hd=0&auth=0&type=flv&tv=0</link>
<thumbnail>http://ia.media-imdb.com/images/M/MV5BMTU2MDY3MzAzMl5BMl5BanBnXkFtZTcwMTg0NjM5NA@@._V1_SX214_.jpg</thumbnail>
</item>

<item>
<title>Eight Below (2006)</title>
</link>http://85.12.8.91/index.php?file=1403&start=0&hd=0&auth=0&type=flv&tv=0</link>
<thumbnail>http://ia.media-imdb.com/images/M/MV5BMjExMjAwNzE0N15BMl5BanBnXkFtZTYwMDY4NDk2._V1_SY317_CR0,0,214,317_.jpg</thumbnail>
</item>

<item>
<title>The Game Plan (2007)</title>
</link>http://85.12.8.91/index.php?file=1402&start=0&hd=0&auth=0&type=flv&tv=0</link>
<thumbnail>http://ia.media-imdb.com/images/M/MV5BMTAzNDIyODYzMTJeQTJeQWpwZ15BbWU3MDA3NTA5NDE@._V1_SY317_CR0,0,214,317_.jpg</thumbnail>
</item>

<item>
<title>Outback (2013)</title>
</link>http://85.12.8.91/index.php?file=1387&start=0&hd=0&auth=0&type=flv&tv=0</link>
<thumbnail>http://ia.media-imdb.com/images/M/MV5BMjExMjYzMzA1MF5BMl5BanBnXkFtZTcwNDA4NjU4Nw@@._V1_SY317_CR4,0,214,317_.jpg</thumbnail>
</item>

<item>
<title>RV (2006)</title>
</link>http://85.12.8.91/index.php?file=1420&start=0&hd=0&auth=0&type=flv&tv=0</link>
<thumbnail>http://ia.media-imdb.com/images/M/MV5BNDgxNDE2NDU3MV5BMl5BanBnXkFtZTcwMzA2ODQzMQ@@._V1_SX214_.jpg</thumbnail>
</item>

<item>
<title>Bedtime Stories (2008)</title>
</link>http://85.12.8.91/index.php?file=1435&start=0&hd=0&auth=0&type=flv&tv=0</link>
<thumbnail>http://ia.media-imdb.com/images/M/MV5BMjA5Njk5MTUxNF5BMl5BanBnXkFtZTcwMDI3MTg5MQ@@._V1_SX214_.jpg</thumbnail>
</item>

<item>
<title>The Muppets (2011)</title>
</link>http://85.12.8.91/index.php?file=1443&start=0&hd=0&auth=0&type=flv&tv=0</link>
<thumbnail>http://ia.media-imdb.com/images/M/MV5BMjE0MTM4NTc3NF5BMl5BanBnXkFtZTcwMjYzOTIxNg@@._V1_SX214_.jpg</thumbnail>
</item>

<item>
<title>Where the Wild Things Are (2009)</title>
</link>http://85.12.8.91/index.php?file=1246&start=0&hd=0&auth=0&type=flv&tv=0</link>
<thumbnail>http://ia.media-imdb.com/images/M/MV5BNzQ1NzAwODEwM15BMl5BanBnXkFtZTcwNTE4MjI4Mg@@._V1_SY317_CR0,0,214,317_.jpg</thumbnail>
</item>

<item>
<title>Balto (1995)</title>
</link>http://85.12.8.91/index.php?file=1259&start=0&hd=0&auth=0&type=flv&tv=0</link>
<thumbnail>http://ia.media-imdb.com/images/M/MV5BMjA4MDQ0Nzc3N15BMl5BanBnXkFtZTYwMTkzODk4._V1_SY317_CR2,0,214,317_.jpg</thumbnail>
</item>

<item>
<title>Balto II: Wolf Quest (2002)</title>
</link>http://85.12.8.91/index.php?file=1260&start=0&hd=0&auth=0&type=flv&tv=0</link>
<thumbnail>http://ia.media-imdb.com/images/M/MV5BNTYzNjgyMzI0OV5BMl5BanBnXkFtZTcwMjQzMDgxMQ@@._V1_SX214_.jpg</thumbnail>
</item>

<item>
<title>Balto III: Wings of Change(2004)</title>
</link>http://85.12.8.91/index.php?file=1261&start=0&hd=0&auth=0&type=flv&tv=0</link>
<thumbnail>http://ia.media-imdb.com/images/M/MV5BMjEyMjg4OTE2OF5BMl5BanBnXkFtZTcwOTQyMzcyMQ@@._V1_SY317_CR4,0,214,317_.jpg</thumbnail>
</item>

<item>
<title>Inkheart (2008)</title>
</link>http://85.12.8.91/index.php?file=1199&start=0&hd=0&auth=0&type=flv&tv=0</link>
<thumbnail>http://ia.media-imdb.com/images/M/MV5BMTg5NTc2MDEwN15BMl5BanBnXkFtZTcwMTA5ODQ5MQ@@._V1_SX214_.jpg</thumbnail>
</item>

<item>
<title>Zathura: A Space Adventure (2005)</title>
</link>http://85.12.8.91/index.php?file=1203&start=0&hd=0&auth=0&type=flv&tv=0</link>
<thumbnail>http://ia.media-imdb.com/images/M/MV5BMjEyOTQ2ODg4OV5BMl5BanBnXkFtZTcwMjk2ODUzMQ@@._V1_SX214_.jpg</thumbnail>
</item>

<item>
<title>Atlantis: The Lost Empire (2001)</title>
</link>http://85.12.8.91/index.php?file=1173&start=0&hd=0&auth=0&type=flv&tv=0</link>
<thumbnail>http://ia.media-imdb.com/images/M/MV5BMjE0MDU2MTQ2M15BMl5BanBnXkFtZTYwOTc5OTI3._V1_SY317_CR14,0,214,317_.jpg</thumbnail>
</item>

<item>
<title>Cinderella (1950)</title>
</link>http://85.12.8.91/index.php?file=1139&start=0&hd=0&auth=0&type=flv&tv=0</link>
<thumbnail>http://ia.media-imdb.com/images/M/MV5BOTQxMDk1OTEyNl5BMl5BanBnXkFtZTYwNjQ0MTA5._V1_SX214_.jpg</thumbnail>
</item>

<item>
<title>Dumbo (1941)</title>
</link>http://85.12.8.91/index.php?file=1138&start=0&hd=0&auth=0&type=flv&tv=0</link>
<thumbnail>http://ia.media-imdb.com/images/M/MV5BMTA2NDQwMzE0MjBeQTJeQWpwZ15BbWU3MDA4ODc4MTU@._V1_SY317_CR7,0,214,317_.jpg</thumbnail>
</item>

<item>
<title>Pinocchio (1940)</title>
</link>http://85.12.8.91/index.php?file=1137&start=0&hd=0&auth=0&type=flv&tv=0</link>
<thumbnail>http://ia.media-imdb.com/images/M/MV5BMTI0Nzk1NTQ2Ml5BMl5BanBnXkFtZTcwNjgyNDIzMg@@._V1_SY317_CR6,0,214,317_.jpg</thumbnail>
</item>

<item>
<title>Bambi (1942)</title>
</link>http://85.12.8.91/index.php?file=1136&start=0&hd=0&auth=0&type=flv&tv=0</link>
<thumbnail>http://ia.media-imdb.com/images/M/MV5BNzA0MzI0MDcxNV5BMl5BanBnXkFtZTcwMTQxMTcyMQ@@._V1_SY317_CR5,0,214,317_.jpg</thumbnail>
</item>

<item>
<title>Alice in Wonderland (1951)</title>
</link>http://85.12.8.91/index.php?file=1135&start=0&hd=0&auth=0&type=flv&tv=0</link>
<thumbnail>http://ia.media-imdb.com/images/M/MV5BMzc4NzE1NjUxNV5BMl5BanBnXkFtZTcwNzc2NDQyMQ@@._V1_SY317_CR4,0,214,317_.jpg</thumbnail>
</item>

<item>
<title>Lady and the Tramp (1955)</title>
</link>http://85.12.8.91/index.php?file=1134&start=0&hd=0&auth=0&type=flv&tv=0</link>
<thumbnail>http://ia.media-imdb.com/images/M/MV5BMjAwNzA3NTk0NV5BMl5BanBnXkFtZTcwMzkyNDEzMQ@@._V1_SY317_CR8,0,214,317_.jpg</thumbnail>
</item>

<item>
<title>The Little Mermaid (1989)</title>
</link>http://85.12.8.91/index.php?file=1174&start=0&hd=0&auth=0&type=flv&tv=0</link>
<thumbnail>http://ia.media-imdb.com/images/M/MV5BNjc0MDQ5MDMzNF5BMl5BanBnXkFtZTcwOTQyOTIzMQ@@._V1_SY317_CR5,0,214,317_.jpg</thumbnail>
</item>

<item>
<title>Aladdin (1992)</title>
</link>http://85.12.8.91/index.php?file=1131&start=0&hd=0&auth=0&type=flv&tv=0</link>
<thumbnail>http://ia.media-imdb.com/images/M/MV5BMjE0ODI0NTM1OV5BMl5BanBnXkFtZTcwODE0MjYyMQ@@._V1_SY317_CR6,0,214,317_.jpg</thumbnail>
</item>

<item>
<title>Sleeping Beauty (1959)</title>
</link>http://85.12.8.91/index.php?file=1133&start=0&hd=0&auth=0&type=flv&tv=0</link>
<thumbnail>http://ia.media-imdb.com/images/M/MV5BMjExODM3ODMyMF5BMl5BanBnXkFtZTcwNjg4MzM2MQ@@._V1_SY317_CR6,0,214,317_.jpg</thumbnail>
</item>

<item>
<title>The Hunchback of Notre Dame (1996)</title>
</link>http://85.12.8.91/index.php?file=1129&start=0&hd=0&auth=0&type=flv&tv=0</link>
<thumbnail>http://ia.media-imdb.com/images/M/MV5BMjE1MDk2MzUxM15BMl5BanBnXkFtZTYwNzc1NTE5._V1_SY317_CR5,0,214,317_.jpg</thumbnail>
</item>

<item>
<title>Hercules (1997)</title>
</link>http://85.12.8.91/index.php?file=1128&start=0&hd=0&auth=0&type=flv&tv=0</link>
<thumbnail>http://ia.media-imdb.com/images/M/MV5BMTI5NTI3OTAyOV5BMl5BanBnXkFtZTcwMTg3ODkxMQ@@._V1_SY317_CR3,0,214,317_.jpg</thumbnail>
</item>

<item>
<title>The Mighty Ducks (1992)</title>
</link>http://85.12.8.91/index.php?file=1130&start=0&hd=0&auth=0&type=flv&tv=0</link>
<thumbnail>http://ia.media-imdb.com/images/M/MV5BMTIzMzgxOTQwMV5BMl5BanBnXkFtZTcwMzkzNDYyMQ@@._V1_SY317_CR5,0,214,317_.jpg</thumbnail>
</item>

<item>
<title>Tinker Bell (2008)</title>
</link>http://85.12.8.91/index.php?file=1127&start=0&hd=0&auth=0&type=flv&tv=0</link>
<thumbnail>http://ia.media-imdb.com/images/M/MV5BMjA4NTQzMDQ2MV5BMl5BanBnXkFtZTcwNzQwODQ2MQ@@._V1_SY317_CR2,0,214,317_.jpg</thumbnail>
</item>

<item>
<title>Tinker Bell and the Great Fairy Rescue (2010)</title>
</link>http://85.12.8.91/index.php?file=1126&start=0&hd=0&auth=0&type=flv&tv=0</link>
<thumbnail>http://ia.media-imdb.com/images/M/MV5BMTcxNDI2MzM4M15BMl5BanBnXkFtZTcwNzA4OTk2Mw@@._V1_SY317_CR6,0,214,317_.jpg</thumbnail>
</item>

<item>
<title>Tinker Bell and the Lost Treasure (2009)</title>
</link>http://85.12.8.91/index.php?file=1125&start=0&hd=0&auth=0&type=flv&tv=0</link>
<thumbnail>http://ia.media-imdb.com/images/M/MV5BMTc3OTc4ODc4OV5BMl5BanBnXkFtZTcwOTEzOTIxMw@@._V1_SY317_CR7,0,214,317_.jpg</thumbnail>
</item>

<item>
<title>Mulan (1998)</title>
</link>http://85.12.8.91/index.php?file=1086&start=0&hd=0&auth=0&type=flv&tv=0</link>
<thumbnail>http://ia.media-imdb.com/images/M/MV5BMTIwNjY4NDU2NF5BMl5BanBnXkFtZTcwMzM0OTUyMQ@@._V1_SY317_CR4,0,214,317_.jpg</thumbnail>
</item>

<item>
<title>Tad, the Lost Explorer (2012)</title>
</link>http://85.12.8.91/index.php?file=1073&start=0&hd=0&auth=0&type=flv&tv=0</link>
<thumbnail>https://encrypted-tbn2.gstatic.com/images?q=tbn:ANd9GcTvN6ultcvvy_tL6ZmcfrTUAIzFoDwoWT8HG1vHE62uhT7htzZU</thumbnail>
</item>

<item>
<title>Ponyo (2008)</title>
</link>http://85.12.8.91/index.php?file=1065&start=0&hd=0&auth=0&type=flv&tv=0</link>
<thumbnail>http://ia.media-imdb.com/images/M/MV5BMjA5NzkxNTg2MF5BMl5BanBnXkFtZTcwMTA3MjU1Mg@@._V1_SY317_CR0,0,214,317_.jpg</thumbnail>
</item>

<item>
<title>Chicken Run (2000)</title>
</link>http://85.12.8.91/index.php?file=963&start=0&hd=0&auth=0&type=flv&tv=0</link>
<thumbnail>http://ia.media-imdb.com/images/M/MV5BMTk1MjE3MjQ0OF5BMl5BanBnXkFtZTcwMTcyMTcyMQ@@._V1_SY317_CR7,0,214,317_.jpg</thumbnail>
</item>

<item>
<title>Rise of the Guardians (2012)</title>
</link>http://85.12.8.91/index.php?file=955&start=0&hd=0&auth=0&type=flv&tv=0</link>
<thumbnail>http://ia.media-imdb.com/images/M/MV5BMTkzMjgwMDg1M15BMl5BanBnXkFtZTcwMTgzNTI1OA@@._V1_SX214_.jpg</thumbnail>
</item>

<item>
<title>Alice in Wonderland (2010)</title>
</link>http://85.12.8.91/index.php?file=1009&start=0&hd=0&auth=0&type=flv&tv=0</link>
<thumbnail>http://ia.media-imdb.com/images/M/MV5BMTMwNjAxMTc0Nl5BMl5BanBnXkFtZTcwODc3ODk5Mg@@._V1_SY317_CR0,0,214,317_.jpg</thumbnail>
</item>

<item>
<title>Jumanji (1995)</title>
</link>http://85.12.8.91/index.php?file=1036&start=0&hd=0&auth=0&type=flv&tv=0</link>
<thumbnail>http://ia.media-imdb.com/images/M/MV5BMzM5NjE1OTMxNV5BMl5BanBnXkFtZTcwNDY2MzEzMQ@@._V1_SY317_CR4,0,214,317_.jpg</thumbnail>
</item>

<item>
<title>Home Alone (1990)</title>
</link>http://85.12.8.91/index.php?file=1042&start=0&hd=0&auth=0&type=flv&tv=0</link>
<thumbnail>http://ia.media-imdb.com/images/M/MV5BMTUzMzg4MTg2M15BMl5BanBnXkFtZTYwNDM4OTk4._V1_SY317_CR6,0,214,317_.jpg</thumbnail>
</item>

<item>
<title>Home Alone 2: Lost in New York (1992)</title>
</link>http://85.12.8.91/index.php?file=1040&start=0&hd=0&auth=0&type=flv&tv=0</link>
<thumbnail>http://ia.media-imdb.com/images/M/MV5BMTYyODQzNDk1OV5BMl5BanBnXkFtZTcwOTM3MTU1MQ@@._V1_SY317_CR5,0,214,317_.jpg</thumbnail>
</item>

<item>
<title>Bridge to Terabithia (2007)</title>
</link>http://85.12.8.91/index.php?file=911&start=0&hd=0&auth=0&type=flv&tv=0</link>
<thumbnail>http://ia.media-imdb.com/images/M/MV5BMTMzOTk1MzIyN15BMl5BanBnXkFtZTcwNTM3MjczMQ@@._V1_SY317_CR0,0,214,317_.jpg</thumbnail>
</item>

<item>
<title>Percy Jackson & the Olympians: The Lightning Thief (2010)</title>
</link>http://85.12.8.91/index.php?file=880&start=0&hd=0&auth=0&type=flv&tv=0</link>
<thumbnail>http://ia.media-imdb.com/images/M/MV5BMTQ0MzY5OTQ2N15BMl5BanBnXkFtZTcwNzI1MTU5Mg@@._V1_SY317_CR0,0,214,317_.jpg</thumbnail>
</item>

<item>
<title>Charlie and the Chocolate Factory (2005)</title>
</link>http://85.12.8.91/index.php?file=914&start=0&hd=0&auth=0&type=flv&tv=0</link>
<thumbnail>http://ia.media-imdb.com/images/M/MV5BNjcxMjg1Njg2NF5BMl5BanBnXkFtZTcwMjQ4NzMzMw@@._V1_SY317_CR0,0,214,317_.jpg</thumbnail>
</item>

<item>
<title>Finding Neverland (2004)</title>
</link>http://85.12.8.91/index.php?file=915&start=0&hd=0&auth=0&type=flv&tv=0</link>
<thumbnail>http://ia.media-imdb.com/images/M/MV5BMTMxNzYzNzUzMV5BMl5BanBnXkFtZTYwNjcwMjE3._V1_SY317_CR0,0,214,317_.jpg</thumbnail>
</item>

<item>
<title>Elf (2003)</title>
</link>http://85.12.8.91/index.php?file=919&start=0&hd=0&auth=0&type=flv&tv=0</link>
<thumbnail>http://ia.media-imdb.com/images/M/MV5BNjY1NjQ3NDY5MF5BMl5BanBnXkFtZTYwODAyMTc3._V1_SX214_.jpg</thumbnail>
</item>

<item>
<title>The Goonies (1985)</title>
</link>http://85.12.8.91/index.php?file=920&start=0&hd=0&auth=0&type=flv&tv=0</link>
<thumbnail>http://ia.media-imdb.com/images/M/MV5BMTY1Mzk3MTg0M15BMl5BanBnXkFtZTcwOTQzODYyMQ@@._V1_SY317_CR3,0,214,317_.jpg</thumbnail>
</item>

<item>
<title>Wreck-It Ralph (2012)</title>
</link>http://85.12.8.91/index.php?file=888&start=0&hd=0&auth=0&type=flv&tv=0</link>
<thumbnail>http://ia.media-imdb.com/images/M/MV5BNzMxNTExOTkyMF5BMl5BanBnXkFtZTcwMzEyNDc0OA@@._V1_SX214_.jpg</thumbnail>
</item>

<item>
<title>Over the Hedge (2006)</title>
</link>http://85.12.8.91/index.php?file=883&start=0&hd=0&auth=0&type=flv&tv=0</link>
<thumbnail>http://ia.media-imdb.com/images/M/MV5BMTQwMTQxNTcwOF5BMl5BanBnXkFtZTcwMzQ1NzUzMQ@@._V1_SX214_.jpg</thumbnail>
</item>

<item>
<title>Open Season (2006)</title>
</link>http://85.12.8.91/index.php?file=868&start=0&hd=0&auth=0&type=flv&tv=0</link>
<thumbnail>http://ia.media-imdb.com/images/M/MV5BMTQwOTg2MjU0OV5BMl5BanBnXkFtZTcwMzIzNTQzMQ@@._V1_SX214_.jpg</thumbnail>
</item>

<item>
<title>Open Season 2 (2008)</title>
</link>http://85.12.8.91/index.php?file=869&start=0&hd=0&auth=0&type=flv&tv=0</link>
<thumbnail>http://ia.media-imdb.com/images/M/MV5BMTYwNjczMDI0MV5BMl5BanBnXkFtZTcwMjY3NDcwMg@@._V1_SY317_CR18,0,214,317_.jpg</thumbnail>
</item>

<item>
<title>Open Season 3 (2010)</title>
</link>http://85.12.8.91/index.php?file=870&start=0&hd=0&auth=0&type=flv&tv=0</link>
<thumbnail>http://ia.media-imdb.com/images/M/MV5BMTk3OTY3NTQ5Nl5BMl5BanBnXkFtZTcwNzQ3OTAxNA@@._V1_SY317_CR26,0,214,317_.jpg</thumbnail>
</item>

<item>
<title>Puss in Boots (2011)</title>
</link>http://85.12.8.91/index.php?file=871&start=0&hd=0&auth=0&type=flv&tv=0</link>
<thumbnail>http://ia.media-imdb.com/images/M/MV5BMTMxMTU5MTY4MV5BMl5BanBnXkFtZTcwNzgyNjg2NQ@@._V1_SX214_.jpg</thumbnail>
</item>

<item>
<title>Cloudy with a Chance of Meatballs (2009)</title>
</link>http://85.12.8.91/index.php?file=872&start=0&hd=0&auth=0&type=flv&tv=0</link>
<thumbnail>http://ia.media-imdb.com/images/M/MV5BMTg0MjAwNDI5MV5BMl5BanBnXkFtZTcwODkyMzg2Mg@@._V1_SX214_.jpg</thumbnail>
</item>

<item>
<title>Bolt (2008)</title>
</link>http://85.12.8.91/index.php?file=867&start=0&hd=0&auth=0&type=flv&tv=0</link>
<thumbnail>http://ia.media-imdb.com/images/M/MV5BNDQyNDE5NjQ1N15BMl5BanBnXkFtZTcwMDExMTAwMg@@._V1_SY317_CR4,0,214,317_.jpg</thumbnail>
</item>

<item>
<title>Monster House (2006)</title>
</link>http://85.12.8.91/index.php?file=866&start=0&hd=0&auth=0&type=flv&tv=0</link>
<thumbnail>http://ia.media-imdb.com/images/M/MV5BMTI4NDY5MzI3MV5BMl5BanBnXkFtZTcwMTI5OTMzMQ@@._V1_SY317_CR0,0,214,317_.jpg</thumbnail>
</item>

<item>
<title>Astro Boy (2009)</title>
</link>http://85.12.8.91/index.php?file=865&start=0&hd=0&auth=0&type=flv&tv=0</link>
<thumbnail>http://ia.media-imdb.com/images/M/MV5BMTI5NTEwNTcxMl5BMl5BanBnXkFtZTcwMDEyMTE4Mg@@._V1_SX214_.jpg</thumbnail>
</item>

<item>
<title>The Polar Express (2004)</title>
</link>http://85.12.8.91/index.php?file=864&start=0&hd=0&auth=0&type=flv&tv=0</link>
<thumbnail>http://ia.media-imdb.com/images/M/MV5BMTM1NTU0NTE4MV5BMl5BanBnXkFtZTcwMTQ0MjEzMw@@._V1_SY317_CR0,0,214,317_.jpg</thumbnail>
</item>

<item>
<title>Coraline (2009)</title>
</link>http://85.12.8.91/index.php?file=861&start=0&hd=0&auth=0&type=flv&tv=0</link>
<thumbnail>http://ia.media-imdb.com/images/M/MV5BMzQxNjM5NzkxNV5BMl5BanBnXkFtZTcwMzg5NDMwMg@@._V1_SX214_.jpg</thumbnail>
</item>

<item>
<title>Kung Fu Panda (2008)</title>
</link>http://85.12.8.91/index.php?file=854&start=0&hd=0&auth=0&type=flv&tv=0</link>
<thumbnail>http://ia.media-imdb.com/images/M/MV5BMTIxOTY1NjUyN15BMl5BanBnXkFtZTcwMjMxMDk1MQ@@._V1_SX214_.jpg</thumbnail>
</item>

<item>
<title>Kung Fu Panda 2 (2011)</title>
</link>http://85.12.8.91/index.php?file=855&start=0&hd=0&auth=0&type=flv&tv=0</link>
<thumbnail>http://ia.media-imdb.com/images/M/MV5BMTg4MTQ3NTI3Nl5BMl5BanBnXkFtZTcwNzEzODQ2NA@@._V1_SX214_.jpg</thumbnail>
</item>

<item>
<title>Happy Feet (2006)</title>
</link>http://85.12.8.91/index.php?file=852&start=0&hd=0&auth=0&type=flv&tv=0</link>
<thumbnail>http://ia.media-imdb.com/images/M/MV5BMTQyNTkxMjUwMV5BMl5BanBnXkFtZTcwMDQ2NTU0MQ@@._V1_SY317_CR0,0,214,317_.jpg</thumbnail>
</item>

<item>
<title>Happy Feet Two (2011)</title>
</link>http://85.12.8.91/index.php?file=853&start=0&hd=0&auth=0&type=flv&tv=0</link>
<thumbnail>http://ia.media-imdb.com/images/M/MV5BMTg1MzU2Nzg2OV5BMl5BanBnXkFtZTcwNzE3MzAxNg@@._V1_SY317_CR0,0,214,317_.jpg</thumbnail>
</item>

<item>
<title>Spirit: Stallion of the Cimarron (2002)</title>
</link>http://85.12.8.91/index.php?file=838&start=0&hd=0&auth=0&type=flv&tv=0</link>
<thumbnail>http://ia.media-imdb.com/images/M/MV5BMTgyOTUzNDA1N15BMl5BanBnXkFtZTYwNjgwMDM3._V1_SY317_CR0,0,214,317_.jpg</thumbnail>
</item>

<item>
<title>The Incredibles (2004)</title>
</link>http://85.12.8.91/index.php?file=839&start=0&hd=0&auth=0&type=flv&tv=0</link>
<thumbnail>http://ia.media-imdb.com/images/M/MV5BMTY5OTU0OTc2NV5BMl5BanBnXkFtZTcwMzU4MDcyMQ@@._V1_SY317_CR0,0,214,317_.jpg</thumbnail>
</item>

<item>
<title>Gnomeo & Juliet (2011)</title>
</link>http://85.12.8.91/index.php?file=840&start=0&hd=0&auth=0&type=flv&tv=0</link>
<thumbnail>http://ia.media-imdb.com/images/M/MV5BMjAyNDM2MDA2NF5BMl5BanBnXkFtZTcwOTMxMDAxNA@@._V1_SX214_.jpg</thumbnail>
</item>

<item>
<title>Ratatouille (2007)</title>
</link>http://85.12.8.91/index.php?file=841&start=0&hd=0&auth=0&type=flv&tv=0</link>
<thumbnail>http://ia.media-imdb.com/images/M/MV5BMTMzODU0NTkxMF5BMl5BanBnXkFtZTcwMjQ4MzMzMw@@._V1_SX214_.jpg</thumbnail>
</item>

<item>
<title>Tangled (2010)</title>
</link>http://85.12.8.91/index.php?file=842&start=0&hd=0&auth=0&type=flv&tv=0</link>
<thumbnail>http://ia.media-imdb.com/images/M/MV5BMjA5NzMwMjA0OV5BMl5BanBnXkFtZTcwNDMzMzc5Mw@@._V1_SX214_.jpg</thumbnail>
</item>

<item>
<title>Surf's Up (2007)</title>
</link>http://85.12.8.91/index.php?file=843&start=0&hd=0&auth=0&type=flv&tv=0</link>
<thumbnail>http://ia.media-imdb.com/images/M/MV5BMjE4NDE3NzcwM15BMl5BanBnXkFtZTcwMTI0ODYzMw@@._V1_SX214_.jpg</thumbnail>
</item>

<item>
<title>Legend of the Guardians: The Owls of Ga'Hoole (2010)</title>
</link>http://85.12.8.91/index.php?file=844&start=0&hd=0&auth=0&type=flv&tv=0</link>
<thumbnail>http://ia.media-imdb.com/images/M/MV5BMjE0NjA5OTA4N15BMl5BanBnXkFtZTcwODA3MTA3Mw@@._V1_SY317_CR0,0,214,317_.jpg</thumbnail>
</item>

<item>
<title>Up (2009)</title>
</link>http://85.12.8.91/index.php?file=845&start=0&hd=0&auth=0&type=flv&tv=0</link>
<thumbnail>http://ia.media-imdb.com/images/M/MV5BMTMwODg0NDY1Nl5BMl5BanBnXkFtZTcwMjkwNTgyMg@@._V1_SX214_.jpg</thumbnail>
</item>

<item>
<title>Winnie the Pooh (2011)</title>
</link>http://85.12.8.91/index.php?file=846&start=0&hd=0&auth=0&type=flv&tv=0</link>
<thumbnail>http://ia.media-imdb.com/images/M/MV5BMjI2MTMxMDYwMl5BMl5BanBnXkFtZTcwMDM0NTQ4NA@@._V1_SX214_.jpg</thumbnail>
</item>

<item>
<title>Yogi Bear (2010)</title>
</link>http://85.12.8.91/index.php?file=847&start=0&hd=0&auth=0&type=flv&tv=0</link>
<thumbnail>http://ia.media-imdb.com/images/M/MV5BMTczMjU1NTQ0M15BMl5BanBnXkFtZTcwMjIxMTA3Mw@@._V1_SX214_.jpg</thumbnail>
</item>

<item>
<title>The Lorax (2012)</title>
</link>http://85.12.8.91/index.php?file=757&start=0&hd=0&auth=0&type=flv&tv=0</link>
<thumbnail>http://ia.media-imdb.com/images/M/MV5BMTU1MTAwMjk1NF5BMl5BanBnXkFtZTcwMDI5NDc4Ng@@._V1_SX214_.jpg</thumbnail>
</item>

<item>
<title>Treasure Planet (2002)</title>
</link>http://85.12.8.91/index.php?file=760&start=0&hd=0&auth=0&type=flv&tv=0</link>
<thumbnail>http://ia.media-imdb.com/images/M/MV5BMTQ0NDg3MjU2OV5BMl5BanBnXkFtZTYwODgyMDg5._V1_SY317_CR0,0,214,317_.jpg</thumbnail>
</item>

<item>
<title>The Spy Next Door (2010)</title>
</link>http://85.12.8.91/index.php?file=758&start=0&hd=0&auth=0&type=flv&tv=0</link>
<thumbnail>http://ia.media-imdb.com/images/M/MV5BMTI5MjEzMjM4N15BMl5BanBnXkFtZTcwODc0ODEwMw@@._V1_SX214_.jpg</thumbnail>
</item>

<item>
<title>Mr. Bean's Holiday (2007)</title>
</link>http://85.12.8.91/index.php?file=763&start=0&hd=0&auth=0&type=flv&tv=0</link>
<thumbnail>http://ia.media-imdb.com/images/M/MV5BMTM2NzQ1Mzc4M15BMl5BanBnXkFtZTcwNTk3NjA1MQ@@._V1_SY317_CR0,0,214,317_.jpg</thumbnail>
</item>

<item>
<title>Cars (2006)</title>
</link>http://85.12.8.91/index.php?file=787&start=0&hd=0&auth=0&type=flv&tv=0</link>
<thumbnail>http://ia.media-imdb.com/images/M/MV5BMTE5Mzk5MTA2Ml5BMl5BanBnXkFtZTYwNTY3NTc2._V1_SY317_CR0,0,214,317_.jpg</thumbnail>
</item>

<item>
<title>Cars 2 (2011)</title>
</link>http://85.12.8.91/index.php?file=788&start=0&hd=0&auth=0&type=flv&tv=0</link>
<thumbnail>http://ia.media-imdb.com/images/M/MV5BMTUzNTc3MTU3M15BMl5BanBnXkFtZTcwMzIxNTc3NA@@._V1_SX214_.jpg</thumbnail>
</item>

<item>
<title>Space Jam (1996)</title>
</link>http://85.12.8.91/index.php?file=789&start=0&hd=0&auth=0&type=flv&tv=0</link>
<thumbnail>http://ia.media-imdb.com/images/M/MV5BMTQ5NDg1NTgwOV5BMl5BanBnXkFtZTcwODAwNDAwMQ@@._V1_SY317_CR11,0,214,317_.jpg</thumbnail>
</item>

<item>
<title>Shrek (2001)</title>
</link>http://85.12.8.91/index.php?file=794&start=0&hd=0&auth=0&type=flv&tv=0</link>
<thumbnail>http://ia.media-imdb.com/images/M/MV5BMzk2MzYwOTY0N15BMl5BanBnXkFtZTcwOTg4NDUxMQ@@._V1_SY317_CR5,0,214,317_.jpg</thumbnail>
</item>

<item>
<title>Shrek 2 (2004)</title>
</link>http://85.12.8.91/index.php?file=795&start=0&hd=0&auth=0&type=flv&tv=0</link>
<thumbnail>http://ia.media-imdb.com/images/M/MV5BMTk4MTMwNjI4M15BMl5BanBnXkFtZTcwMjExMzUyMQ@@._V1_SX214_.jpg</thumbnail>
</item>

<item>
<title>Shrek the Third (2007)</title>
</link>http://85.12.8.91/index.php?file=796&start=0&hd=0&auth=0&type=flv&tv=0</link>
<thumbnail>http://ia.media-imdb.com/images/M/MV5BMTMyMjE1Mjc1NF5BMl5BanBnXkFtZTcwMzY0MjEzMw@@._V1_SX214_.jpg</thumbnail>
</item>

<item>
<title>Shrek Forever After (2010)</title>
</link>http://85.12.8.91/index.php?file=797&start=0&hd=0&auth=0&type=flv&tv=0</link>
<thumbnail>http://ia.media-imdb.com/images/M/MV5BMTY0OTU1NzkxMl5BMl5BanBnXkFtZTcwMzI2NDUzMw@@._V1_SX214_.jpg</thumbnail>
</item>

<item>
<title>Tarzan (1999)</title>
</link>http://85.12.8.91/index.php?file=798&start=0&hd=0&auth=0&type=flv&tv=0</link>
<thumbnail>http://ia.media-imdb.com/images/M/MV5BMTIxNzY1MDg2Ml5BMl5BanBnXkFtZTcwMDgxMDEzMQ@@._V1_SY317_CR3,0,214,317_.jpg</thumbnail>
</item>

<item>
<title>How to Train Your Dragon (2010)</title>
</link>http://85.12.8.91/index.php?file=799&start=0&hd=0&auth=0&type=flv&tv=0</link>
<thumbnail>http://ia.media-imdb.com/images/M/MV5BMjA5NDQyMjc2NF5BMl5BanBnXkFtZTcwMjg5ODcyMw@@._V1_SX214_.jpg</thumbnail>
</item>

<item>
<title>The Lion King (1994)</title>
</link>http://85.12.8.91/index.php?file=835&start=0&hd=0&auth=0&type=flv&tv=0</link>
<thumbnail>http://ia.media-imdb.com/images/M/MV5BMjEyMzgwNTUzMl5BMl5BanBnXkFtZTcwNTMxMzM3Ng@@._V1_SY317_CR15,0,214,317_.jpg</thumbnail>
</item>

<item>
<title>The Lion King 2: Simba's Pride (1998)</title>
</link>http://85.12.8.91/index.php?file=836&start=0&hd=0&auth=0&type=flv&tv=0</link>
<thumbnail>http://ia.media-imdb.com/images/M/MV5BMTI5ODU4Mzc5OF5BMl5BanBnXkFtZTcwNzU3NTYyMQ@@._V1_SY317_CR4,0,214,317_.jpg</thumbnail>
</item>

<item>
<title>The Lion King 1 1/2 (2004)</title>
</link>http://85.12.8.91/index.php?file=837&start=0&hd=0&auth=0&type=flv&tv=0</link>
<thumbnail>http://ia.media-imdb.com/images/M/MV5BMjAyNjE3MTkzMF5BMl5BanBnXkFtZTYwNzc3NDg2._V1_SY317_CR7,0,214,317_.jpg</thumbnail>
</item>

<item>
<title>Spy Kids (2001)</title>
</link>http://85.12.8.91/index.php?file=674&start=0&hd=0&auth=0&type=flv&tv=0</link>
<thumbnail>http://ia.media-imdb.com/images/M/MV5BMTczMDE0NDY5M15BMl5BanBnXkFtZTcwOTg4NDgxMQ@@._V1_SY317_CR5,0,214,317_.jpg</thumbnail>
</item>

<item>
<title>Spy Kids 2: Island of Lost Dreams (2002)</title>
</link>http://85.12.8.91/index.php?file=675&start=0&hd=0&auth=0&type=flv&tv=0</link>
<thumbnail>http://ia.media-imdb.com/images/M/MV5BMTM0NzA1Njg2NF5BMl5BanBnXkFtZTYwNzA1MTg5._V1_SY317_CR5,0,214,317_.jpg</thumbnail>
</item>

<item>
<title>Spy Kids 3D: Game Over (2003)</title>
</link>http://85.12.8.91/index.php?file=676&start=0&hd=0&auth=0&type=flv&tv=0</link>
<thumbnail>http://ia.media-imdb.com/images/M/MV5BMTI4MTQyNTUzMF5BMl5BanBnXkFtZTcwNzE2MDAwMQ@@._V1_SY317_CR1,0,214,317_.jpg</thumbnail>
</item>

<item>
<title>Spy Kids 4D: All the Time in the World (2011)</title>
</link>http://85.12.8.91/index.php?file=677&start=0&hd=0&auth=0&type=flv&tv=0</link>
<thumbnail>http://ia.media-imdb.com/images/M/MV5BMTgwOTk1NjQ0NV5BMl5BanBnXkFtZTcwNTk4MDI3NQ@@._V1_SY317_CR0,0,214,317_.jpg</thumbnail>
</item>

<item>
<title>Robots (2005)</title>
</link>http://85.12.8.91/index.php?file=550&start=0&hd=0&auth=0&type=flv&tv=0</link>
<thumbnail>http://ia.media-imdb.com/images/M/MV5BNDYyNjY1NjY1M15BMl5BanBnXkFtZTcwNjk5MDczMw@@._V1_SY317_CR0,0,214,317_.jpg</thumbnail>
</item>

<item>
<title>Short Circuit (1986)</title>
</link>http://85.12.8.91/index.php?file=665&start=0&hd=0&auth=0&type=flv&tv=0</link>
<thumbnail>http://ia.media-imdb.com/images/M/MV5BMTM3NzIwNjE4OV5BMl5BanBnXkFtZTcwNjk0MTUxMQ@@._V1_SY317_CR9,0,214,317_.jpg</thumbnail>
</item>

<item>
<title>Hotel Transylvania (2012)</title>
</link>http://85.12.8.91/index.php?file=654&start=0&hd=0&auth=0&type=flv&tv=0</link>
<thumbnail>http://ia.media-imdb.com/images/M/MV5BMTM3NjQyODI3M15BMl5BanBnXkFtZTcwMDM4NjM0OA@@._V1_SX214_.jpg</thumbnail>
</item>

<item>
<title>Dinosaur (2000)</title>
</link>http://85.12.8.91/index.php?file=593&start=0&hd=0&auth=0&type=flv&tv=0</link>
<thumbnail>http://ia.media-imdb.com/images/M/MV5BMjA4OTUwNTIzOV5BMl5BanBnXkFtZTYwNzE3MjQ3._V1_SY317_CR3,0,214,317_.jpg</thumbnail>
</item>

<item>
<title>Sky High (2005)</title>
</link>http://85.12.8.91/index.php?file=549&start=0&hd=0&auth=0&type=flv&tv=0</link>
<thumbnail>http://ia.media-imdb.com/images/M/MV5BMTMzODg4MTc0NV5BMl5BanBnXkFtZTcwOTU0MzkzMQ@@._V1_SY317_CR5,0,214,317_.jpg</thumbnail>
</item>

<item>
<title>The Princess and the Frog (2009)</title>
</link>http://85.12.8.91/index.php?file=684&start=0&hd=0&auth=0&type=flv&tv=0</link>
<thumbnail>http://ia.media-imdb.com/images/M/MV5BMjEyOTQ5NzAzNl5BMl5BanBnXkFtZTcwMTcyNTU1Mg@@._V1_SX214_.jpg</thumbnail>
</item>

<item>
<title>Pocahontas (1995)</title>
</link>http://85.12.8.91/index.php?file=495&start=0&hd=0&auth=0&type=flv&tv=0</link>
<thumbnail>http://ia.media-imdb.com/images/M/MV5BMTU2ODI2NzI4OF5BMl5BanBnXkFtZTYwMjk5NzA5._V1_SY317_CR2,0,214,317_.jpg</thumbnail>
</item>

<item>
<title>Hop (2011)</title>
</link>http://85.12.8.91/index.php?file=432&start=0&hd=0&auth=0&type=flv&tv=0</link>
<thumbnail>http://ia.media-imdb.com/images/M/MV5BMTY4MDcxNTkzNV5BMl5BanBnXkFtZTcwMTg2MDY2NA@@._V1_SY317_CR0,0,214,317_.jpg</thumbnail>
</item>

<item>
<title>Journey 2: The Mysterious Island (2012)</title>
</link>http://85.12.8.91/index.php?file=430&start=0&hd=0&auth=0&type=flv&tv=0</link>
<thumbnail>http://ia.media-imdb.com/images/M/MV5BMjA5MTE1MjQyNV5BMl5BanBnXkFtZTcwODI4NDMwNw@@._V1_SX214_.jpg</thumbnail>
</item>

<item>
<title>The Sound of Music (1965)</title>
</link>http://85.12.8.91/index.php?file=421&start=0&hd=0&auth=0&type=flv&tv=0</link>
<thumbnail>http://ia.media-imdb.com/images/M/MV5BMTY0MzA3MDk2M15BMl5BanBnXkFtZTcwODg4MzEzMQ@@._V1_SY317_CR5,0,214,317_.jpg</thumbnail>
</item>

<item>
<title>The Pirates! Band of Misfits (2012)</title>
</link>http://85.12.8.91/index.php?file=396&start=0&hd=0&auth=0&type=flv&tv=0</link>
<thumbnail>http://ia.media-imdb.com/images/M/MV5BOTkzOTc1OTg1Ml5BMl5BanBnXkFtZTcwMjg2ODcwNg@@._V1_SX214_.jpg</thumbnail>
</item>

<item>
<title>Last Ounce of Courage (2012)</title>
</link>http://85.12.8.91/index.php?file=382&start=0&hd=0&auth=0&type=flv&tv=0</link>
<thumbnail>http://ia.media-imdb.com/images/M/MV5BMTY5NjA1NTgzMl5BMl5BanBnXkFtZTcwNDk5MTQ0OA@@._V1_SX214_.jpg</thumbnail>
</item>

<item>
<title>Ice Age (2002)</title>
</link>http://85.12.8.91/index.php?file=358&start=0&hd=0&auth=0&type=flv&tv=0</link>
<thumbnail>http://ia.media-imdb.com/images/M/MV5BMjEyNzI1ODA0MF5BMl5BanBnXkFtZTYwODIxODY3._V1_SX214_.jpg</thumbnail>
</item>

<item>
<title>Ice Age: The Meltdown (2006)</title>
</link>http://85.12.8.91/index.php?file=359&start=0&hd=0&auth=0&type=flv&tv=0</link>
<thumbnail>http://ia.media-imdb.com/images/M/MV5BMjAwODg3OTAxMl5BMl5BanBnXkFtZTcwMjg2NjYyMw@@._V1_SY317_CR0,0,214,317_.jpg</thumbnail>
</item>

<item>
<title>Ice Age: Dawn of the Dinosaurs (2009)</title>
</link>http://85.12.8.91/index.php?file=360&start=0&hd=0&auth=0&type=flv&tv=0</link>
<thumbnail>http://ia.media-imdb.com/images/M/MV5BMjA4NDI0Mjg4NV5BMl5BanBnXkFtZTcwOTM1NTY0Mg@@._V1_SY317_CR7,0,214,317_.jpg</thumbnail>
</item>

<item>
<title>Ice Age: Continental Drift (2012)</title>
</link>http://85.12.8.91/index.php?file=149&start=0&hd=0&auth=0&type=flv&tv=0</link>
<thumbnail>http://ia.media-imdb.com/images/M/MV5BMTM3NDM5MzY5Ml5BMl5BanBnXkFtZTcwNjExMDUwOA@@._V1_SX214_.jpg</thumbnail>
</item>

<item>
<title>Toy Story (1995)</title>
</link>http://85.12.8.91/index.php?file=342&start=0&hd=0&auth=0&type=flv&tv=0</link>
<thumbnail>http://ia.media-imdb.com/images/M/MV5BMTgwMjI4MzU5N15BMl5BanBnXkFtZTcwMTMyNTk3OA@@._V1_SY317_CR12,0,214,317_.jpg</thumbnail>
</item>

<item>
<title>Toy Story 2 (1999)</title>
</link>http://85.12.8.91/index.php?file=339&start=0&hd=0&auth=0&type=flv&tv=0</link>
<thumbnail>http://ia.media-imdb.com/images/M/MV5BMTQ0OTU0NTcyNl5BMl5BanBnXkFtZTcwOTk5Mjc4OA@@._V1_SY317_CR12,0,214,317_.jpg</thumbnail>
</item>

<item>
<title>Toy Story 3 (2010)</title>
</link>http://85.12.8.91/index.php?file=338&start=0&hd=0&auth=0&type=flv&tv=0</link>
<thumbnail>http://ia.media-imdb.com/images/M/MV5BMTgxOTY4Mjc0MF5BMl5BanBnXkFtZTcwNTA4MDQyMw@@._V1_SY317_CR5,0,214,317_.jpg</thumbnail>
</item>

<item>
<title>Horton Hears a Who! (2008)</title>
</link>http://85.12.8.91/index.php?file=318&start=0&hd=0&auth=0&type=flv&tv=0</link>
<thumbnail>http://ia.media-imdb.com/images/M/MV5BMTI3NDA3ODE0N15BMl5BanBnXkFtZTcwNjE0MzU1MQ@@._V1_SY317_CR5,0,214,317_.jpg</thumbnail>
</item>

<item>
<title>Zambezia (2012)</title>
</link>http://85.12.8.91/index.php?file=296&start=0&hd=0&auth=0&type=flv&tv=0</link>
<thumbnail>http://ia.media-imdb.com/images/M/MV5BNTEyNzE5MDc3NF5BMl5BanBnXkFtZTcwNjA3MzAxOA@@._V1_SY317_CR0,0,214,317_.jpg</thumbnail>
</item>

<item>
<title>The Nightmare Before Christmas (1993)</title>
</link>http://85.12.8.91/index.php?file=289&start=0&hd=0&auth=0&type=flv&tv=0</link>
<thumbnail>http://ia.media-imdb.com/images/M/MV5BMTc5MDY0MjkwNV5BMl5BanBnXkFtZTcwNTk2Njk3OA@@._V1_SY317_CR12,0,214,317_.jpg</thumbnail>
</item>

<item>
<title>Hocus Pocus (1993)</title>
</link>http://85.12.8.91/index.php?file=274&start=0&hd=0&auth=0&type=flv&tv=0</link>
<thumbnail>http://ia.media-imdb.com/images/M/MV5BMTI3MDI2NDc3Ml5BMl5BanBnXkFtZTcwNDQ2MzQyMQ@@._V1_SY317_CR3,0,214,317_.jpg</thumbnail>
</item>

<item>
<title>WALL·E (2008)</title>
</link>http://85.12.8.91/index.php?file=267&start=0&hd=0&auth=0&type=flv&tv=0</link>
<thumbnail>http://ia.media-imdb.com/images/M/MV5BMTczOTA3MzY2N15BMl5BanBnXkFtZTcwOTYwNjE2MQ@@._V1_SY317_CR0,0,214,317_.jpg</thumbnail>
</item>

<item>
<title>Diary of a Wimpy Kid: Dog Days (2012)</title>
</link>http://85.12.8.91/index.php?file=257&start=0&hd=0&auth=0&type=flv&tv=0</link>
<thumbnail>http://ia.media-imdb.com/images/M/MV5BMTc2MTk4MTk4Nl5BMl5BanBnXkFtZTcwMzgzOTY2Nw@@._V1_SX214_.jpg</thumbnail>
</item>

<item>
<title>101 Dalmatians II: Patch's London Adventure (2003)</title>
</link>http://85.12.8.91/index.php?file=243&start=0&hd=0&auth=0&type=flv&tv=0</link>
<thumbnail>http://ia.media-imdb.com/images/M/MV5BOTc4OTQ2MTA5OV5BMl5BanBnXkFtZTcwNzI4NzcxMQ@@._V1_SY317_CR5,0,214,317_.jpg</thumbnail>
</item>

<item>
<title> Old Dogs (2009)</title>
</link>http://85.12.8.91/index.php?file=228&start=0&hd=0&auth=0&type=flv&tv=0</link>
<thumbnail>http://ia.media-imdb.com/images/M/MV5BMjExMTYyMzk3MV5BMl5BanBnXkFtZTcwMzI2Njg0Mg@@._V1_SX214_.jpg</thumbnail>
</item>

<item>
<title>College Road Trip (2008)</title>
</link>http://85.12.8.91/index.php?file=227&start=0&hd=0&auth=0&type=flv&tv=0</link>
<thumbnail>http://ia.media-imdb.com/images/M/MV5BMTc5NjM4Njg1NF5BMl5BanBnXkFtZTcwMDE2OTc1MQ@@._V1_SY317_CR0,0,214,317_.jpg</thumbnail>
</item>

<item>
<title>Rango (2011)</title>
</link>http://85.12.8.91/index.php?file=225&start=0&hd=0&auth=0&type=flv&tv=0</link>
<thumbnail>http://ia.media-imdb.com/images/M/MV5BMjE5ODg1NTk3OF5BMl5BanBnXkFtZTcwNzA5NTMyNA@@._V1_SX214_.jpg</thumbnail>
</item>

<item>
<title>Race to Witch Mountain (2009)</title>
</link>http://85.12.8.91/index.php?file=209&start=0&hd=0&auth=0&type=flv&tv=0</link>
<thumbnail>http://ia.media-imdb.com/images/M/MV5BMzQ5MTM5NTU2NV5BMl5BanBnXkFtZTcwMDAzMjAyMg@@._V1_SY317_CR0,0,214,317_.jpg</thumbnail>
</item>

<item>
<title>Monsters, Inc. (2001)</title>
</link>http://85.12.8.91/index.php?file=199&start=0&hd=0&auth=0&type=flv&tv=0</link>
<thumbnail>http://ia.media-imdb.com/images/M/MV5BMTk0NzAwMzI5MF5BMl5BanBnXkFtZTcwMjM4MTM0OA@@._V1_SX214_.jpg</thumbnail>
</item>

<item>
<title>Fantastic Mr. Fox (2009)</title>
</link>http://85.12.8.91/index.php?file=195&start=0&hd=0&auth=0&type=flv&tv=0</link>
<thumbnail>http://ia.media-imdb.com/images/M/MV5BMTcwODE2NTI3Nl5BMl5BanBnXkFtZTcwMjUwOTY5Mg@@._V1_SX214_.jpg</thumbnail>
</item>

<item>
<title>Monsters vs Aliens (2009)</title>
</link>http://85.12.8.91/index.php?file=190&start=0&hd=0&auth=0&type=flv&tv=0</link>
<thumbnail>http://ia.media-imdb.com/images/M/MV5BMTY0OTQ3MzE3MV5BMl5BanBnXkFtZTcwMDQyMzMzMg@@._V1_SX214_.jpg</thumbnail>
</item>

<item>
<title>The Last Airbender (2010)</title>
</link>http://85.12.8.91/index.php?file=189&start=0&hd=0&auth=0&type=flv&tv=0</link>
<thumbnail>http://ia.media-imdb.com/images/M/MV5BMTM1NjE0NDA0MV5BMl5BanBnXkFtZTcwODE4NDg1Mw@@._V1_SX214_.jpg</thumbnail>
</item>

<item>
<title>ParaNorman (2012)</title>
</link>http://85.12.8.91/index.php?file=175&start=0&hd=0&auth=0&type=flv&tv=0</link>
<thumbnail>http://ia.media-imdb.com/images/M/MV5BMjA1OTU1NDM3N15BMl5BanBnXkFtZTcwMjYxNTg0Nw@@._V1_SX214_.jpg</thumbnail>
</item>

<item>
<title>Hook (1991)</title>
</link>http://85.12.8.91/index.php?file=161&start=0&hd=0&auth=0&type=flv&tv=0</link>
<thumbnail>http://ia.media-imdb.com/images/M/MV5BMTUzMTUxNDE2Nl5BMl5BanBnXkFtZTcwNDUwNjcyMQ@@._V1_SY317_CR2,0,214,317_.jpg</thumbnail>
</item>

<item>
<title>Meet the Robinsons (2007)</title>
</link>http://85.12.8.91/index.php?file=159&start=0&hd=0&auth=0&type=flv&tv=0</link>
<thumbnail>http://ia.media-imdb.com/images/M/MV5BMTg0NTU4MDY5OV5BMl5BanBnXkFtZTcwMzY0MjM0MQ@@._V1_SY317_CR0,0,214,317_.jpg</thumbnail>
</item>

<item>
<title>Secret of the Wings (2012)</title>
</link>http://85.12.8.91/index.php?file=154&start=0&hd=0&auth=0&type=flv&tv=0</link>
<thumbnail>http://ia.media-imdb.com/images/M/MV5BMTYwMjI1MDIzMl5BMl5BanBnXkFtZTcwMTM4Nzc5Nw@@._V1_SY317_CR12,0,214,317_.jpg</thumbnail>
</item>

<item>
<title>Aliens in the Attic (2009)</title>
</link>http://85.12.8.91/index.php?file=90&start=0&hd=0&auth=0&type=flv&tv=0</link>
<thumbnail>http://ia.media-imdb.com/images/M/MV5BMTk3NTMzNTIxNV5BMl5BanBnXkFtZTcwOTI4ODU1Mg@@._V1_SY317_CR0,0,214,317_.jpg</thumbnail>
</item>

<item>
<title>Arthur Christmas (2011)</title>
</link>http://85.12.8.91/index.php?file=84&start=0&hd=0&auth=0&type=flv&tv=0</link>
<thumbnail>http://ia.media-imdb.com/images/M/MV5BMTYyMjMyMzEzMl5BMl5BanBnXkFtZTcwMDg4NTM5Ng@@._V1_SY317_CR0,0,214,317_.jpg</thumbnail>
</item>

<item>
<title>The Tale of Despereaux (2008)</title>
</link>http://85.12.8.91/index.php?file=74&start=0&hd=0&auth=0&type=flv&tv=0</link>
<thumbnail>http://ia.media-imdb.com/images/M/MV5BMTg0MTc5MTc1MV5BMl5BanBnXkFtZTcwNjgwNDE4MQ@@._V1_SY317_CR0,0,214,317_.jpg</thumbnail>
</item>

<item>
<title>Madagascar (2005)</title>
</link>http://85.12.8.91/index.php?file=14&start=0&hd=0&auth=0&type=flv&tv=0</link>
<thumbnail>http://ia.media-imdb.com/images/M/MV5BMTY4NDUwMzQxMF5BMl5BanBnXkFtZTcwMDgwNjgyMQ@@._V1_SX214_.jpg</thumbnail>
</item>

<item>
<title>Madagascar: Escape 2 Africa (2008)</title>
</link>http://85.12.8.91/index.php?file=17&start=0&hd=0&auth=0&type=flv&tv=0</link>
<thumbnail>http://ia.media-imdb.com/images/M/MV5BMjExMDA4NDcwMl5BMl5BanBnXkFtZTcwODAxNTQ3MQ@@._V1_SX214_.jpg</thumbnail>
</item>

<item>
<title>Madagascar 3: Europe's Most Wanted (2012)</title>
</link>http://85.12.8.91/index.php?file=21&start=0&hd=0&auth=0&type=flv&tv=0</link>
<thumbnail>http://ia.media-imdb.com/images/M/MV5BMTM2MTIzNzk2MF5BMl5BanBnXkFtZTcwMDcwMzQxNw@@._V1_SY317_CR0,0,214,317_.jpg</thumbnail>
</item>

<item>
<title>Finding Nemo (2003)</title>
</link>http://85.12.8.91/index.php?file=13&start=0&hd=0&auth=0&type=flv&tv=0</link>
<thumbnail>http://ia.media-imdb.com/images/M/MV5BMTY1MTg1NDAxOV5BMl5BanBnXkFtZTcwMjg1MDI5Nw@@._V1_SY317_CR0,0,214,317_.jpg</thumbnail>
</item>

<item>
<title>Meet Dave (2008)</title>
</link>http://85.12.8.91/index.php?file=9&start=0&hd=0&auth=0&type=flv&tv=0</link>
<thumbnail>http://ia.media-imdb.com/images/M/MV5BMjExMjIzODc0M15BMl5BanBnXkFtZTcwMTk0MjQ2MQ@@._V1_SX214_.jpg</thumbnail>
</item>

<item>
<title>Brave (2012)</title>
</link>http://85.12.8.91/index.php?file=2&start=0&hd=0&auth=0&type=flv&tv=0</link>
<thumbnail>http://ia.media-imdb.com/images/M/MV5BMzgwODk3ODA1NF5BMl5BanBnXkFtZTcwNjU3NjQ0Nw@@._V1._SX500_SY999_.jpg</thumbnail>
</item>
